rankpy/__init__.py
rankpy/process_example.py
rankpy/rank.py
rankpy/tests/test_hodge_rank.py
rankpy/tests/test_raw_conversion.py
rankpy-0.4.1.dist-info/WHEEL
rankpy-0.4.1.dist-info/METADATA
rankpy-0.4.1.dist-info/RECORD
