Metadata-Version: 2.1
Name: rankpy
Version: 0.4.1
Summary: Package which creates a single, ranked order of charges from multiple lists of rankings.
Author-email: Kevin Himberger & JJ Naddeo <kevin.himberger@justiceinnovationlab.org>
Requires-Python: >=3.10
Requires-Dist: jenkspy
Project-URL: home-page, https://github.com:Justice-Innovation-Lab/rankpy
